saoovqe/__init__.py
saoovqe/ansatz.py
saoovqe/circuits.py
saoovqe/gradient.py
saoovqe/logger_config.py
saoovqe/molecule.py
saoovqe/problem.py
saoovqe/pso.py
saoovqe/vqe_optimization.py
saoovqe-1.2.0.dist-info/METADATA
saoovqe-1.2.0.dist-info/WHEEL
saoovqe-1.2.0.dist-info/licenses/LICENSE.md
saoovqe-1.2.0.dist-info/RECORD
