Metadata-Version: 2.4
Name: saoovqe
Version: 1.2.0
Summary: SA-OO-VQE method implemented via Qiskit library
Project-URL: Homepage, https://gitlab.com/MartinBeseda/sa-oo-vqe-qiskit.git
Project-URL: Documentation, https://sa-oo-vqe-qiskit.readthedocs.io/en/latest/
Author-email: Martin Beseda <martinbeseda@seznam.cz>, Silvie Illésová <silvie.illesova@seznam.cz>, Saad Yalouz <yalouzsaad@gmail.com>, Bruno Senjean <bsenjean@gmail.com>
License: State-Averaged Orbital-Optimized VQE
License-File: LICENSE.md
Classifier: License :: OSI Approved :: GNU General Public License v3 (GPLv3)
Classifier: Operating System :: POSIX :: Linux
Classifier: Programming Language :: Python :: 3
Requires-Python: >=3.12
